{
  "youtube": {
    "UC-8QAzbLcRglXeN_MY9blyw": {
      "type": "video",
      "title": "Explaining Programming Memes part 1 #shorts",
      "videoId": "Lwy-tyh1QBI",
      "author": "Ben Awad",
      "authorId": "UC-8QAzbLcRglXeN_MY9blyw",
      "videoThumbnails": [
        {
          "url": "https://i.ytimg.com/vi/Lwy-tyh1QBI/hqdefault.jpg?sqp=-oaymwEiCKgBEF5IWvKriqkDFQgBFQAAAAAYASUAAMhCPQCAokN4AQ==&rs=AOn4CLCMMoJ0RfXbssfvdO5e83K5gPzASQ",
          "width": 168,
          "height": 94
        },
        {
          "url": "https://i.ytimg.com/vi/Lwy-tyh1QBI/hqdefault.jpg?sqp=-oaymwEiCMQBEG5IWvKriqkDFQgBFQAAAAAYASUAAMhCPQCAokN4AQ==&rs=AOn4CLBBMqzlFNyFU-s71OrLDHwofRBCPA",
          "width": 196,
          "height": 110
        },
        {
          "url": "https://i.ytimg.com/vi/Lwy-tyh1QBI/hqdefault.jpg?sqp=-oaymwEjCPYBEIoBSFryq4qpAxUIARUAAAAAGAElAADIQj0AgKJDeAE=&rs=AOn4CLBlPwsvyiIvN2WoYoXtrv35_o7xXQ",
          "width": 246,
          "height": 138
        },
        {
          "url": "https://i.ytimg.com/vi/Lwy-tyh1QBI/hqdefault.jpg?sqp=-oaymwEjCNACELwBSFryq4qpAxUIARUAAAAAGAElAADIQj0AgKJDeAE=&rs=AOn4CLAgRBZf3FFAumON4FW_9qrI7LVSGw",
          "width": 336,
          "height": 188
        }
      ],
      "viewCountText": "722 views",
      "viewCount": 722,
      "publishedText": "10 minutes ago",
      "durationText": "0:27",
      "lengthSeconds": 27,
      "liveNow": false,
      "premiere": false,
      "premium": false
    },
    "Fireship": {
      "type": "video",
      "title": "Vite in 100 Seconds",
      "videoId": "KCrXgy8qtjM",
      "author": "Fireship",
      "authorId": "Fireship",
      "videoThumbnails": [
        {
          "url": "https://i.ytimg.com/vi/KCrXgy8qtjM/hqdefault.jpg?sqp=-oaymwEiCKgBEF5IWvKriqkDFQgBFQAAAAAYASUAAMhCPQCAokN4AQ==&rs=AOn4CLBCrDdIs6Ozpmu2Af93UDp-PzwVuw",
          "width": 168,
          "height": 94
        },
        {
          "url": "https://i.ytimg.com/vi/KCrXgy8qtjM/hqdefault.jpg?sqp=-oaymwEiCMQBEG5IWvKriqkDFQgBFQAAAAAYASUAAMhCPQCAokN4AQ==&rs=AOn4CLB4sRo--jmvchOySSOyk9ji7LfCvg",
          "width": 196,
          "height": 110
        },
        {
          "url": "https://i.ytimg.com/vi/KCrXgy8qtjM/hqdefault.jpg?sqp=-oaymwEjCPYBEIoBSFryq4qpAxUIARUAAAAAGAElAADIQj0AgKJDeAE=&rs=AOn4CLDg2ocusas1jkCuppo4S7AuKAElRg",
          "width": 246,
          "height": 138
        },
        {
          "url": "https://i.ytimg.com/vi/KCrXgy8qtjM/hqdefault.jpg?sqp=-oaymwEjCNACELwBSFryq4qpAxUIARUAAAAAGAElAADIQj0AgKJDeAE=&rs=AOn4CLDZKan_11G_mHCbwUb33H2RTVo0kQ",
          "width": 336,
          "height": 188
        }
      ],
      "viewCountText": "5,630 views",
      "viewCount": 5630,
      "publishedText": "15 minutes ago",
      "durationText": "2:29",
      "lengthSeconds": 149,
      "liveNow": false,
      "premiere": false,
      "premium": false
    },
    "UCWr0mx597DnSGLFk1WfvSkQ": {
      "type": "video",
      "title": "A FULL DAY OF CODE",
      "videoId": "b1yGhE_rDSw",
      "author": "Kalle Hallden",
      "authorId": "UCWr0mx597DnSGLFk1WfvSkQ",
      "videoThumbnails": [
        {
          "url": "https://i.ytimg.com/vi/b1yGhE_rDSw/hqdefault.jpg?sqp=-oaymwEiCKgBEF5IWvKriqkDFQgBFQAAAAAYASUAAMhCPQCAokN4AQ==&rs=AOn4CLCn8DvmWpYdIN6VSAMYsnnpjIcHcQ",
          "width": 168,
          "height": 94
        },
        {
          "url": "https://i.ytimg.com/vi/b1yGhE_rDSw/hqdefault.jpg?sqp=-oaymwEiCMQBEG5IWvKriqkDFQgBFQAAAAAYASUAAMhCPQCAokN4AQ==&rs=AOn4CLBvFp3uABTJj_PAM5yk3DqZ543tSw",
          "width": 196,
          "height": 110
        },
        {
          "url": "https://i.ytimg.com/vi/b1yGhE_rDSw/hqdefault.jpg?sqp=-oaymwEjCPYBEIoBSFryq4qpAxUIARUAAAAAGAElAADIQj0AgKJDeAE=&rs=AOn4CLBJSF255_Lxy6Owo_0kAEnxVGLp4A",
          "width": 246,
          "height": 138
        },
        {
          "url": "https://i.ytimg.com/vi/b1yGhE_rDSw/hqdefault.jpg?sqp=-oaymwEjCNACELwBSFryq4qpAxUIARUAAAAAGAElAADIQj0AgKJDeAE=&rs=AOn4CLA1qve85BY2zhU7S8gIXgdwJotXpw",
          "width": 336,
          "height": 188
        }
      ],
      "viewCountText": "951 views",
      "viewCount": 951,
      "publishedText": "15 minutes ago",
      "durationText": "10:13",
      "lengthSeconds": 613,
      "liveNow": false,
      "premiere": false,
      "premium": false
    },
    "UCc4IizbM0q_JySK3XUY0Drw": {
      "type": "video",
      "title": "TOP PAYING PROGRAMMING JOBS",
      "videoId": "e9G5MfWxPeU",
      "author": "zyapguy",
      "authorId": "UCc4IizbM0q_JySK3XUY0Drw",
      "videoThumbnails": [
        {
          "url": "https://i.ytimg.com/vi/e9G5MfWxPeU/hqdefault.jpg?sqp=-oaymwEiCKgBEF5IWvKriqkDFQgBFQAAAAAYASUAAMhCPQCAokN4AQ==&rs=AOn4CLDZQw62VMrvMWjRqsnOo5Yt3Zm-vQ",
          "width": 168,
          "height": 94
        },
        {
          "url": "https://i.ytimg.com/vi/e9G5MfWxPeU/hqdefault.jpg?sqp=-oaymwEiCMQBEG5IWvKriqkDFQgBFQAAAAAYASUAAMhCPQCAokN4AQ==&rs=AOn4CLAk5zQr_-cptlU4KSv8jwyr3FDdRQ",
          "width": 196,
          "height": 110
        },
        {
          "url": "https://i.ytimg.com/vi/e9G5MfWxPeU/hqdefault.jpg?sqp=-oaymwEjCPYBEIoBSFryq4qpAxUIARUAAAAAGAElAADIQj0AgKJDeAE=&rs=AOn4CLAtqTphri7lTp5ADclGSLrgFYYHxA",
          "width": 246,
          "height": 138
        },
        {
          "url": "https://i.ytimg.com/vi/e9G5MfWxPeU/hqdefault.jpg?sqp=-oaymwEjCNACELwBSFryq4qpAxUIARUAAAAAGAElAADIQj0AgKJDeAE=&rs=AOn4CLBcs73eupd0WUXBEiXg40B1ZYUaKA",
          "width": 336,
          "height": 188
        }
      ],
      "viewCountText": "96 views",
      "viewCount": 96,
      "publishedText": "4 minutes ago",
      "durationText": "7:53",
      "lengthSeconds": 473,
      "liveNow": false,
      "premiere": false,
      "premium": false
    },
    "JomaOppa": {
      "type": "video",
      "title": "nft traders be like...",
      "videoId": "JgdP7oWP0_0",
      "author": "Joma Tech",
      "authorId": "JomaOppa",
      "videoThumbnails": [
        {
          "url": "https://i.ytimg.com/vi/JgdP7oWP0_0/hqdefault.jpg?sqp=-oaymwEiCKgBEF5IWvKriqkDFQgBFQAAAAAYASUAAMhCPQCAokN4AQ==&rs=AOn4CLDyQ9oR3XtIGc1P418rmWO-h0rKTw",
          "width": 168,
          "height": 94
        },
        {
          "url": "https://i.ytimg.com/vi/JgdP7oWP0_0/hqdefault.jpg?sqp=-oaymwEiCMQBEG5IWvKriqkDFQgBFQAAAAAYASUAAMhCPQCAokN4AQ==&rs=AOn4CLC1_xsGYmMO17XVzMNOyA24paojKQ",
          "width": 196,
          "height": 110
        },
        {
          "url": "https://i.ytimg.com/vi/JgdP7oWP0_0/hqdefault.jpg?sqp=-oaymwEjCPYBEIoBSFryq4qpAxUIARUAAAAAGAElAADIQj0AgKJDeAE=&rs=AOn4CLDaREaN3BkBxA9tM8sHDnAETSu6PQ",
          "width": 246,
          "height": 138
        },
        {
          "url": "https://i.ytimg.com/vi/JgdP7oWP0_0/hqdefault.jpg?sqp=-oaymwEjCNACELwBSFryq4qpAxUIARUAAAAAGAElAADIQj0AgKJDeAE=&rs=AOn4CLCoYP0n-pMja_UhUWcjIxPHB3zpjw",
          "width": 336,
          "height": 188
        }
      ],
      "viewCountText": "1,153 views",
      "viewCount": 1153,
      "publishedText": "3 minutes ago",
      "durationText": "3:56",
      "lengthSeconds": 236,
      "liveNow": false,
      "premiere": false,
      "premium": false
    }
  },
  "podcast": {
    "https://feeds.simplecast.com/fJGOlywC": {
      "creator": "contact.laura.kankaala@gmail.com (laura kankaala, antti kurittu, juho jauhiainen)",
      "title": "Episodi 85 - Kyborgit",
      "link": "https://turvakarajat.fi/episodes/episodi-85-kyborgit-X3aGkdpz",
      "pubDate": "Mon, 21 Feb 2022 04:00:00 +0000",
      "author": "contact.laura.kankaala@gmail.com (laura kankaala, antti kurittu, juho jauhiainen)",
      "content:encoded": "<p>WithSecure<br /><a href=\"https://withsecure.com/\">https://withsecure.com/</a></p><p>First.org Symbosium<br /><a href=\"https://www.first.org/events/symposium/regional%5C_europe2022/\">https://www.first.org/events/symposium/regional\\_europe2022/</a></p><p>Nintendon pelejä ja laitteita piratisoinut Gary Bowserin tuomio</p><p><a href=\"https://portswigger.net/daily-swig/nintendo-switch-hacker-sent-behind-bars-owes-video-game-giant-further-4-5m\">https://portswigger.net/daily-swig/nintendo-switch-hacker-sent-behind-bars-owes-video-game-giant-further-4-5m</a></p><p>Nintendo ei halua modaus- ja hakkerointiyhteisöä ekosysteemiinsä</p><p><a href=\"https://techraptor.net/gaming/news/nintendo-leak-reveals-extreme-measures-taken-to-track-hackers\">https://techraptor.net/gaming/news/nintendo-leak-reveals-extreme-measures-taken-to-track-hackers</a></p><p><a href=\"https://screenrant.com/nintendo-leak-hacking-3ds-ds/\">https://screenrant.com/nintendo-leak-hacking-3ds-ds/</a></p><p>Silmäimplantti yritys konkurssiin</p><p><a href=\"https://spectrum.ieee.org/bionic-eye-obsolete\">https://spectrum.ieee.org/bionic-eye-obsolete</a></p><p>Ukrainan DDoS hyökkäykset Privatbankiin ja Oschadbankiin</p><p><a href=\"https://www.zdnet.com/article/ukraine-ministry-of-defense-confirms-ddos-attack-state-banks-loses-connectivity/\">https://www.zdnet.com/article/ukraine-ministry-of-defense-confirms-ddos-attack-state-banks-loses-connectivity/</a></p><p>Twitteristä löytyviä keskusteluja liittyen väärennettyihin pankkiautomaatti viesteihin</p><p><a href=\"https://twitter.com/campuscodi/status/1493581446371586055?s=20&t=t5zWBYWg5Q2GuHJhYcogcA\">https://twitter.com/campuscodi/status/1493581446371586055?s=20&t=t5zWBYWg5Q2GuHJhYcogcA</a></p>\n",
      "content:encodedSnippet": "WithSecure\nhttps://withsecure.com/\nFirst.org Symbosium\nhttps://www.first.org/events/symposium/regional\\_europe2022/\nNintendon pelejä ja laitteita piratisoinut Gary Bowserin tuomio\nhttps://portswigger.net/daily-swig/nintendo-switch-hacker-sent-behind-bars-owes-video-game-giant-further-4-5m\nNintendo ei halua modaus- ja hakkerointiyhteisöä ekosysteemiinsä\nhttps://techraptor.net/gaming/news/nintendo-leak-reveals-extreme-measures-taken-to-track-hackers\nhttps://screenrant.com/nintendo-leak-hacking-3ds-ds/\nSilmäimplantti yritys konkurssiin\nhttps://spectrum.ieee.org/bionic-eye-obsolete\nUkrainan DDoS hyökkäykset Privatbankiin ja Oschadbankiin\nhttps://www.zdnet.com/article/ukraine-ministry-of-defense-confirms-ddos-attack-state-banks-loses-connectivity/\nTwitteristä löytyviä keskusteluja liittyen väärennettyihin pankkiautomaatti viesteihin\nhttps://twitter.com/campuscodi/status/1493581446371586055?s=20&t=t5zWBYWg5Q2GuHJhYcogcA",
      "enclosure": {
        "length": "66368979",
        "type": "audio/mpeg",
        "url": "https://cdn.simplecast.com/audio/beefbca9-0f83-4ffa-b5c0-4cd26da1c1c9/episodes/5d52f82c-bd91-4d29-a5ba-a4d2654faa5c/audio/db25b894-3243-4fd4-aac6-4bcd60855578/default_tc.mp3?aid=rss_feed&feed=fJGOlywC"
      },
      "content": "<p>WithSecure<br /><a href=\"https://withsecure.com/\">https://withsecure.com/</a></p><p>First.org Symbosium<br /><a href=\"https://www.first.org/events/symposium/regional%5C_europe2022/\">https://www.first.org/events/symposium/regional\\_europe2022/</a></p><p>Nintendon pelejä ja laitteita piratisoinut Gary Bowserin tuomio</p><p><a href=\"https://portswigger.net/daily-swig/nintendo-switch-hacker-sent-behind-bars-owes-video-game-giant-further-4-5m\">https://portswigger.net/daily-swig/nintendo-switch-hacker-sent-behind-bars-owes-video-game-giant-further-4-5m</a></p><p>Nintendo ei halua modaus- ja hakkerointiyhteisöä ekosysteemiinsä</p><p><a href=\"https://techraptor.net/gaming/news/nintendo-leak-reveals-extreme-measures-taken-to-track-hackers\">https://techraptor.net/gaming/news/nintendo-leak-reveals-extreme-measures-taken-to-track-hackers</a></p><p><a href=\"https://screenrant.com/nintendo-leak-hacking-3ds-ds/\">https://screenrant.com/nintendo-leak-hacking-3ds-ds/</a></p><p>Silmäimplantti yritys konkurssiin</p><p><a href=\"https://spectrum.ieee.org/bionic-eye-obsolete\">https://spectrum.ieee.org/bionic-eye-obsolete</a></p><p>Ukrainan DDoS hyökkäykset Privatbankiin ja Oschadbankiin</p><p><a href=\"https://www.zdnet.com/article/ukraine-ministry-of-defense-confirms-ddos-attack-state-banks-loses-connectivity/\">https://www.zdnet.com/article/ukraine-ministry-of-defense-confirms-ddos-attack-state-banks-loses-connectivity/</a></p><p>Twitteristä löytyviä keskusteluja liittyen väärennettyihin pankkiautomaatti viesteihin</p><p><a href=\"https://twitter.com/campuscodi/status/1493581446371586055?s=20&t=t5zWBYWg5Q2GuHJhYcogcA\">https://twitter.com/campuscodi/status/1493581446371586055?s=20&t=t5zWBYWg5Q2GuHJhYcogcA</a></p>\n",
      "contentSnippet": "WithSecure\nhttps://withsecure.com/\nFirst.org Symbosium\nhttps://www.first.org/events/symposium/regional\\_europe2022/\nNintendon pelejä ja laitteita piratisoinut Gary Bowserin tuomio\nhttps://portswigger.net/daily-swig/nintendo-switch-hacker-sent-behind-bars-owes-video-game-giant-further-4-5m\nNintendo ei halua modaus- ja hakkerointiyhteisöä ekosysteemiinsä\nhttps://techraptor.net/gaming/news/nintendo-leak-reveals-extreme-measures-taken-to-track-hackers\nhttps://screenrant.com/nintendo-leak-hacking-3ds-ds/\nSilmäimplantti yritys konkurssiin\nhttps://spectrum.ieee.org/bionic-eye-obsolete\nUkrainan DDoS hyökkäykset Privatbankiin ja Oschadbankiin\nhttps://www.zdnet.com/article/ukraine-ministry-of-defense-confirms-ddos-attack-state-banks-loses-connectivity/\nTwitteristä löytyviä keskusteluja liittyen väärennettyihin pankkiautomaatti viesteihin\nhttps://twitter.com/campuscodi/status/1493581446371586055?s=20&t=t5zWBYWg5Q2GuHJhYcogcA",
      "guid": "4782e143-c057-4882-add8-d27baa4f0f19",
      "isoDate": "2022-02-21T04:00:00.000Z",
      "itunes": {
        "author": "laura kankaala, antti kurittu, juho jauhiainen",
        "subtitle": "ONNEA LEIJONAT! TORILLA TAVATAAN! Ei vaan, Turvakäräjät pysyvät sisällä ja puhuvat tiukkaa kyberiä. Aiheina Nintendon lakikeissi ja siihen erittäin löyhästi liittyvä modausyhteisö, silmäimplantit ja Ukrainan tilanne.",
        "summary": "ONNEA LEIJONAT! TORILLA TAVATAAN! Ei vaan, Turvakäräjät pysyvät sisällä ja puhuvat tiukkaa kyberiä. Aiheina Nintendon lakikeissi ja siihen erittäin löyhästi liittyvä modausyhteisö, silmäimplantit ja Ukrainan tilanne.",
        "explicit": "yes",
        "duration": "01:09:05",
        "episode": "85",
        "keywords": "laura kankaala, antti kurittu, polestar, ukraina, aiven.io, iot, nixu, hakkerointi, first, juho jauhiainen, tietoturva, first.org, withsecure, withoutsecure, nintendo"
      }
    },
    "https://hakkerit.libsyn.com/rss": {
      "title": "Johtaminen kyberkriisissä | 0x19",
      "link": "https://hakkerit.libsyn.com/johtaminen-kyberkriisiss-0x19",
      "pubDate": "Wed, 09 Feb 2022 06:28:19 +0000",
      "content:encoded": "Tervetuloa Jaettujen Salaisuuksien alppimajalle. Yhä useampi yrityksiä koskettava kriisi liittyy nykyään kyberturvaan. Johtaminen on keskiössä kaikissa kriistitilanteissa ja siksi tässä erikoisjaksossa keskustelemme johtamisesta kyberkriiseissä. Nostamme esille esimerkkejä hyvästä ja huonosta johtamisesta erilaisissa kriisitilanteissa ja lisäksi käymme läpi kohta kohdalta miten toimia akuutissa poikkeamatilanteessa.  <p>Äänijulkaisun lähdeluettelo:</p> <p dir=\"auto\">Myrskyn Silmässä -kirja <a href=\"https://haku.helmet.fi/iii/encore/record/C__Rb2017387\" target=\"_blank\" rel= \"nofollow noopener noreferrer\">https://haku.helmet.fi/iii/encore/record/C__Rb2017387</a></p>",
      "content:encodedSnippet": "Tervetuloa Jaettujen Salaisuuksien alppimajalle. Yhä useampi yrityksiä koskettava kriisi liittyy nykyään kyberturvaan. Johtaminen on keskiössä kaikissa kriistitilanteissa ja siksi tässä erikoisjaksossa keskustelemme johtamisesta kyberkriiseissä. Nostamme esille esimerkkejä hyvästä ja huonosta johtamisesta erilaisissa kriisitilanteissa ja lisäksi käymme läpi kohta kohdalta miten toimia akuutissa poikkeamatilanteessa.  \nÄänijulkaisun lähdeluettelo:\n Myrskyn Silmässä -kirja https://haku.helmet.fi/iii/encore/record/C__Rb2017387",
      "enclosure": {
        "length": "73135167",
        "type": "audio/mpeg",
        "url": "https://traffic.libsyn.com/secure/hakkerit/Johtaminen_kyberkriisissa_2022_1.mp3?dest-id=1518941"
      },
      "content": "Tervetuloa Jaettujen Salaisuuksien alppimajalle. Yhä useampi yrityksiä koskettava kriisi liittyy nykyään kyberturvaan. Johtaminen on keskiössä kaikissa kriistitilanteissa ja siksi tässä erikoisjaksossa keskustelemme johtamisesta kyberkriiseissä. Nostamme esille esimerkkejä hyvästä ja huonosta johtamisesta erilaisissa kriisitilanteissa ja lisäksi käymme läpi kohta kohdalta miten toimia akuutissa poikkeamatilanteessa.  <p>Äänijulkaisun lähdeluettelo:</p> <p dir=\"auto\">Myrskyn Silmässä -kirja<br /> <a href=\"https://haku.helmet.fi/iii/encore/record/C__Rb2017387\" target=\"_blank\" rel= \"nofollow noopener noreferrer\">https://haku.helmet.fi/iii/encore/record/C__Rb2017387</a></p>",
      "contentSnippet": "Tervetuloa Jaettujen Salaisuuksien alppimajalle. Yhä useampi yrityksiä koskettava kriisi liittyy nykyään kyberturvaan. Johtaminen on keskiössä kaikissa kriistitilanteissa ja siksi tässä erikoisjaksossa keskustelemme johtamisesta kyberkriiseissä. Nostamme esille esimerkkejä hyvästä ja huonosta johtamisesta erilaisissa kriisitilanteissa ja lisäksi käymme läpi kohta kohdalta miten toimia akuutissa poikkeamatilanteessa.  \nÄänijulkaisun lähdeluettelo:\n Myrskyn Silmässä -kirja\n https://haku.helmet.fi/iii/encore/record/C__Rb2017387",
      "guid": "79fd4b41-ba60-4140-b1ad-744cd77a04df",
      "isoDate": "2022-02-09T06:28:19.000Z",
      "itunes": {
        "subtitle": "Tervetuloa Jaettujen Salaisuuksien alppimajalle. Yhä useampi yrityksiä koskettava kriisi liittyy nykyään kyberturvaan. Johtaminen on keskiössä kaikissa kriistitilanteissa ja siksi tässä erikoisjaksossa keskustelemme johtamisesta...",
        "explicit": "false",
        "duration": "38:06",
        "image": "https://ssl-static.libsyn.com/p/assets/5/5/d/5/55d52b91e4848626a04421dee9605cbd/herrasmieshakkerit_2500x2500_web-20220209-7dzbyh8n49.jpg",
        "keywords": ""
      }
    },
    "https://anchor.fm/s/5fad03b8/podcast/rss": {
      "creator": "Lounastauko",
      "title": "15. Minna Salinmäki - Työnohjaus on työelämän kausihuoltoa, työkyvyn ylläpitoa",
      "link": "https://anchor.fm/jms-tehdas/episodes/15--Minna-Salinmki---Tynohjaus-on-tyelmn-kausihuoltoa--tykyvyn-yllpitoa-e1adaiq",
      "pubDate": "Wed, 17 Nov 2021 07:57:03 GMT",
      "enclosure": {
        "url": "https://anchor.fm/s/5fad03b8/podcast/play/43477018/https%3A%2F%2Fd3ctxlq1ktw2nl.cloudfront.net%2Fstaging%2F2021-10-17%2F43b04b37-a0f7-3277-4c82-3b58778cca2d.mp3",
        "length": "39203590",
        "type": "audio/mpeg"
      },
      "dc:creator": "Lounastauko",
      "content": "<p>Tämän viikon jaksossa vieraana on Työnohjaus Ajantaikaa yrittäjä ja NLP-kouluttaja Minna Salinmäki.</p>\n<p>Jaksossa keskustellaan paljon työnohjauksesta: mitä työnohjaus on, missä tilanteissa työnohjausta voisi käyttää ja kuinka työnohjaukseen tullaan. Ei tarvita kriisiä, vaan työnohjaus tulisi nähdä työn ja työntekemisen kehittämisen välineenä. Se antaa työkaluja oman työn tutkimiseen, arviointiin ja kehittämiseen, jolloin työntekijän hyvinvointi, työn laatu ja työn tuottavuus on mahdollista parantua. Tottakai keskustellaan myös Minnan työurasta ja yritystoiminnasta luopumisesta sekä Jämsästä. Jämsästä Minna totetaan, että meillä on täällä kaikki hyvän elämän perustarpeet tässä käsillä. &nbsp;&nbsp;&nbsp;&nbsp;</p>\n<p>Minna on toiminut yrittäjänä jo vuodesta 1993 lähtien. Inhimillisyys ja ihmisten auttaminen ovat olleet Minnan perusarvoja alusta alkaen. Vuoteen 2018 asti työn ytimessä oli toimintaterapia, joka kasvoi yhden naisen yrityksestä noin 10 henkilön työyhteisöksi. Jo vuonna 2015 toimintaterapian rinnalle tuli työnohjauksen prosesseja. Lopulta vuonna 2018 Minna luopui rakkaasta lapsestaan ja myi toimintaterapiayrityksen, jotta aikaa jäi enemmän itselle, itsen kehittämiselle ja työnohjaukselle. Samalla Minna jatkoi jo 90-luvulla alkaneita opintoja ja on kouluttautunut NLP-osaajaksi, josta on tullut tärkeä työkalu työnohjausprosesseissa. Ensi syksynä käynnistyy myös Minnan vetämä NLP-koulutuskin.</p>\n<p>Ota yhteyttä Minnaan:</p>\n<p>FB: <a href=\"https://www.facebook.com/tyonohjausajantaikaa\" target=\"_blank\"><strong>@tyonohjausajantaikaa</strong></a></p>\n<p>IG: <a href=\"https://www.instagram.com/tyonohjaus_ajantaikaa/\" target=\"_blank\"><strong>@tyonohjaus_ajantaikaa</strong></a></p>\n<p>WWW: <a href=\"http://www.tyonohjausajantaikaa.fi/\" target=\"_blank\"><strong>tyonohjausajantaikaa.fi</strong></a></p>\n<p>EMAIL: <a href=\"mailto:minna.salinmaki@tyonohjausajantaikaa.fi\" target=\"_blank\"><strong>minna.salinmaki@tyonohjausajantaikaa.fi</strong></a></p>\n<p><br></p>\n<p>Jakson hostaaja: Petteri Koskinen</p>\n<p>#jämsätehdas #jämsä #etätyötila #lounastaukopodcast</p>\n<p>___________________________________________________________________</p>\n<p>Jämsä Tehtaan etätyötilassa kohtaavat erilaiset ihmiset ja erilaiset tarinat. Lounastauko vie ruokapöytäkeskustelut astetta pidemmälle ja antaa äänen pikkukaupungin osaamiselle ja tietotaidolle. Podcast-pöydän ääressä nostetaan esiin piilossa olevia jämsäläisten henkilö- ja yritystarinoita ja käsitellään työelämää sekä työn tekemistä erilaisista näkökulmista.</p>\n<p>Vieraile kulisseissa ja tutustu Lounastauon tukikohtaan Jämsä Tehtaaseen:</p>\n<p>WWW: <a href=\"https://jamsatehdas.fi/\"><strong>jamsatehdas.fi</strong></a></p>\n<p>IG: <a href=\"https://www.instagram.com/jamsatehdas\"><strong>@jamsatehdas</strong></a></p>\n<p>FB: <a href=\"https://www.facebook.com/jamsatehdas\"><strong>Jämsä Tehdas</strong></a></p>\n",
      "contentSnippet": "Tämän viikon jaksossa vieraana on Työnohjaus Ajantaikaa yrittäjä ja NLP-kouluttaja Minna Salinmäki.\nJaksossa keskustellaan paljon työnohjauksesta: mitä työnohjaus on, missä tilanteissa työnohjausta voisi käyttää ja kuinka työnohjaukseen tullaan. Ei tarvita kriisiä, vaan työnohjaus tulisi nähdä työn ja työntekemisen kehittämisen välineenä. Se antaa työkaluja oman työn tutkimiseen, arviointiin ja kehittämiseen, jolloin työntekijän hyvinvointi, työn laatu ja työn tuottavuus on mahdollista parantua. Tottakai keskustellaan myös Minnan työurasta ja yritystoiminnasta luopumisesta sekä Jämsästä. Jämsästä Minna totetaan, että meillä on täällä kaikki hyvän elämän perustarpeet tässä käsillä.     \nMinna on toiminut yrittäjänä jo vuodesta 1993 lähtien. Inhimillisyys ja ihmisten auttaminen ovat olleet Minnan perusarvoja alusta alkaen. Vuoteen 2018 asti työn ytimessä oli toimintaterapia, joka kasvoi yhden naisen yrityksestä noin 10 henkilön työyhteisöksi. Jo vuonna 2015 toimintaterapian rinnalle tuli työnohjauksen prosesseja. Lopulta vuonna 2018 Minna luopui rakkaasta lapsestaan ja myi toimintaterapiayrityksen, jotta aikaa jäi enemmän itselle, itsen kehittämiselle ja työnohjaukselle. Samalla Minna jatkoi jo 90-luvulla alkaneita opintoja ja on kouluttautunut NLP-osaajaksi, josta on tullut tärkeä työkalu työnohjausprosesseissa. Ensi syksynä käynnistyy myös Minnan vetämä NLP-koulutuskin.\nOta yhteyttä Minnaan:\nFB: @tyonohjausajantaikaa\nIG: @tyonohjaus_ajantaikaa\nWWW: tyonohjausajantaikaa.fi\nEMAIL: minna.salinmaki@tyonohjausajantaikaa.fi\n\nJakson hostaaja: Petteri Koskinen\n#jämsätehdas #jämsä #etätyötila #lounastaukopodcast\n___________________________________________________________________\nJämsä Tehtaan etätyötilassa kohtaavat erilaiset ihmiset ja erilaiset tarinat. Lounastauko vie ruokapöytäkeskustelut astetta pidemmälle ja antaa äänen pikkukaupungin osaamiselle ja tietotaidolle. Podcast-pöydän ääressä nostetaan esiin piilossa olevia jämsäläisten henkilö- ja yritystarinoita ja käsitellään työelämää sekä työn tekemistä erilaisista näkökulmista.\nVieraile kulisseissa ja tutustu Lounastauon tukikohtaan Jämsä Tehtaaseen:\nWWW: jamsatehdas.fi\nIG: @jamsatehdas\nFB: Jämsä Tehdas",
      "guid": "b0d00fd6-7055-42e3-a1cb-ad1860d0b0b7",
      "isoDate": "2021-11-17T07:57:03.000Z",
      "itunes": {
        "summary": "<p>Tämän viikon jaksossa vieraana on Työnohjaus Ajantaikaa yrittäjä ja NLP-kouluttaja Minna Salinmäki.</p>\n<p>Jaksossa keskustellaan paljon työnohjauksesta: mitä työnohjaus on, missä tilanteissa työnohjausta voisi käyttää ja kuinka työnohjaukseen tullaan. Ei tarvita kriisiä, vaan työnohjaus tulisi nähdä työn ja työntekemisen kehittämisen välineenä. Se antaa työkaluja oman työn tutkimiseen, arviointiin ja kehittämiseen, jolloin työntekijän hyvinvointi, työn laatu ja työn tuottavuus on mahdollista parantua. Tottakai keskustellaan myös Minnan työurasta ja yritystoiminnasta luopumisesta sekä Jämsästä. Jämsästä Minna totetaan, että meillä on täällä kaikki hyvän elämän perustarpeet tässä käsillä. &nbsp;&nbsp;&nbsp;&nbsp;</p>\n<p>Minna on toiminut yrittäjänä jo vuodesta 1993 lähtien. Inhimillisyys ja ihmisten auttaminen ovat olleet Minnan perusarvoja alusta alkaen. Vuoteen 2018 asti työn ytimessä oli toimintaterapia, joka kasvoi yhden naisen yrityksestä noin 10 henkilön työyhteisöksi. Jo vuonna 2015 toimintaterapian rinnalle tuli työnohjauksen prosesseja. Lopulta vuonna 2018 Minna luopui rakkaasta lapsestaan ja myi toimintaterapiayrityksen, jotta aikaa jäi enemmän itselle, itsen kehittämiselle ja työnohjaukselle. Samalla Minna jatkoi jo 90-luvulla alkaneita opintoja ja on kouluttautunut NLP-osaajaksi, josta on tullut tärkeä työkalu työnohjausprosesseissa. Ensi syksynä käynnistyy myös Minnan vetämä NLP-koulutuskin.</p>\n<p>Ota yhteyttä Minnaan:</p>\n<p>FB: <a href=\"https://www.facebook.com/tyonohjausajantaikaa\" target=\"_blank\"><strong>@tyonohjausajantaikaa</strong></a></p>\n<p>IG: <a href=\"https://www.instagram.com/tyonohjaus_ajantaikaa/\" target=\"_blank\"><strong>@tyonohjaus_ajantaikaa</strong></a></p>\n<p>WWW: <a href=\"http://www.tyonohjausajantaikaa.fi/\" target=\"_blank\"><strong>tyonohjausajantaikaa.fi</strong></a></p>\n<p>EMAIL: <a href=\"mailto:minna.salinmaki@tyonohjausajantaikaa.fi\" target=\"_blank\"><strong>minna.salinmaki@tyonohjausajantaikaa.fi</strong></a></p>\n<p><br></p>\n<p>Jakson hostaaja: Petteri Koskinen</p>\n<p>#jämsätehdas #jämsä #etätyötila #lounastaukopodcast</p>\n<p>___________________________________________________________________</p>\n<p>Jämsä Tehtaan etätyötilassa kohtaavat erilaiset ihmiset ja erilaiset tarinat. Lounastauko vie ruokapöytäkeskustelut astetta pidemmälle ja antaa äänen pikkukaupungin osaamiselle ja tietotaidolle. Podcast-pöydän ääressä nostetaan esiin piilossa olevia jämsäläisten henkilö- ja yritystarinoita ja käsitellään työelämää sekä työn tekemistä erilaisista näkökulmista.</p>\n<p>Vieraile kulisseissa ja tutustu Lounastauon tukikohtaan Jämsä Tehtaaseen:</p>\n<p>WWW: <a href=\"https://jamsatehdas.fi/\"><strong>jamsatehdas.fi</strong></a></p>\n<p>IG: <a href=\"https://www.instagram.com/jamsatehdas\"><strong>@jamsatehdas</strong></a></p>\n<p>FB: <a href=\"https://www.facebook.com/jamsatehdas\"><strong>Jämsä Tehdas</strong></a></p>\n",
        "explicit": "No",
        "duration": "3516",
        "image": "https://d3t3ozftmdmh3i.cloudfront.net/production/podcast_uploaded_episode/15951742/15951742-1637135496225-21a167a78c336.jpg",
        "episode": "15",
        "season": "1"
      }
    }
  }
}